gzint/__init__.py
gzint/main.py
gzint/tests.py
gzint-0.0.4.dist-info/DESCRIPTION.rst
gzint-0.0.4.dist-info/METADATA
gzint-0.0.4.dist-info/RECORD
gzint-0.0.4.dist-info/WHEEL
gzint-0.0.4.dist-info/metadata.json
gzint-0.0.4.dist-info/top_level.txt
