Metadata-Version: 2.0
Name: gzint
Version: 0.0.4
Summary: A library for storing huge integeters efficiently.
Home-page: https://github.com/pirate/gzint
Author: Nick Sweeting
Author-email: gzint@sweeting.me
License: MIT
Keywords: int bigint integers memory gzip storage compression math
Platform: UNKNOWN
Classifier: Development Status :: 3 - Alpha
Classifier: Intended Audience :: Developers
Classifier: Topic :: Utilities
Classifier: Programming Language :: Python :: 3 :: Only
Classifier: License :: OSI Approved :: MIT License
Classifier: Programming Language :: Python :: 3.5
